{
  "version": "v15",
  "training_samples": 32,
  "features_used": [
    "consensus_safety",
    "raw_edge",
    "elo_difference",
    "form_difference",
    "competition_importance",
    "context_reliability"
  ],
  "missing_features": [
    "market_model_gap"
  ],
  "feature_ranking": [
    {
      "feature": "Consensus safety",
      "column": "consensus_safety",
      "samples": 32,
      "wins": 9,
      "losses": 23,
      "winrate": 0.2812,
      "average_value": 0.3457
    },
    {
      "feature": "Raw edge",
      "column": "raw_edge",
      "samples": 32,
      "wins": 9,
      "losses": 23,
      "winrate": 0.2812,
      "average_value": 0.1576
    },
    {
      "feature": "ELO separation",
      "column": "elo_difference",
      "samples": 32,
      "wins": 9,
      "losses": 23,
      "winrate": 0.2812,
      "average_value": 5.304
    },
    {
      "feature": "Form separation",
      "column": "form_difference",
      "samples": 32,
      "wins": 9,
      "losses": 23,
      "winrate": 0.2812,
      "average_value": 0.1632
    },
    {
      "feature": "Competition importance",
      "column": "competition_importance",
      "samples": 32,
      "wins": 9,
      "losses": 23,
      "winrate": 0.2812,
      "average_value": 0.3075
    },
    {
      "feature": "Context reliability",
      "column": "context_reliability",
      "samples": 32,
      "wins": 9,
      "losses": 23,
      "winrate": 0.2812,
      "average_value": 0.2406
    }
  ],
  "warning": "Small sample size - information only",
  "weight_update_allowed": false
}