[
  {
    "datum_iso":"2026-05-10T14:45:00+00:00",
    "datum_display":"10.05.2026 16:45",
    "league":"Eredivisie",
    "zapas":"For Sittard vs Zwolle",
    "home_team":"For Sittard",
    "away_team":"Zwolle",
    "tip":"Over 2.5",
    "market":"totals",
    "kurz":1.5,
    "prob_model":0.8291,
    "edge":0.24365,
    "lh":2.934,
    "la":1.591,
    "vklad":30.0,
    "bookmaker":"William Hill",
    "ai_prob":0.56492,
    "score":38.0713,
    "source_hash":"da5768b6a5c03b20622bb513",
    "implied_prob":0.66667,
    "fair_odds":1.206,
    "ev_eur":7.31,
    "risk_level":"HIGH"
  },
  {
    "datum_iso":"2026-05-08T18:30:00+00:00",
    "datum_display":"08.05.2026 20:30",
    "league":"Bundesliga",
    "zapas":"Dortmund vs Ein Frankfurt",
    "home_team":"Dortmund",
    "away_team":"Ein Frankfurt",
    "tip":"1",
    "market":"h2h",
    "kurz":1.68,
    "prob_model":0.74402,
    "edge":0.24996,
    "lh":3.125,
    "la":1.251,
    "vklad":29.41,
    "bookmaker":"Unibet (FR)",
    "ai_prob":0.56492,
    "score":37.593,
    "source_hash":"10fd92c87da280465e95be6a",
    "implied_prob":0.59524,
    "fair_odds":1.344,
    "ev_eur":7.35,
    "risk_level":"HIGH"
  },
  {
    "datum_iso":"2026-05-10T17:30:00+00:00",
    "datum_display":"10.05.2026 19:30",
    "league":"Bundesliga",
    "zapas":"Mainz vs Union Berlin",
    "home_team":"Mainz",
    "away_team":"Union Berlin",
    "tip":"1",
    "market":"h2h",
    "kurz":1.73,
    "prob_model":0.72089,
    "edge":0.24714,
    "lh":2.418,
    "la":0.846,
    "vklad":27.08,
    "bookmaker":"888sport",
    "ai_prob":0.56492,
    "score":37.0572,
    "source_hash":"912f471d91f029cd977c6460",
    "implied_prob":0.57803,
    "fair_odds":1.387,
    "ev_eur":6.69,
    "risk_level":"HIGH"
  },
  {
    "datum_iso":"2026-05-09T11:30:00+00:00",
    "datum_display":"09.05.2026 13:30",
    "league":"Premier League",
    "zapas":"Liverpool vs Chelsea",
    "home_team":"Liverpool",
    "away_team":"Chelsea",
    "tip":"1",
    "market":"h2h",
    "kurz":1.78,
    "prob_model":0.62494,
    "edge":0.11239,
    "lh":2.534,
    "la":1.38,
    "vklad":11.53,
    "bookmaker":"Winamax (FR)",
    "ai_prob":0.52007,
    "score":24.2276,
    "source_hash":"b51cc159706cfe61f9b36a19",
    "implied_prob":0.5618,
    "fair_odds":1.6,
    "ev_eur":1.3,
    "risk_level":"MEDIUM"
  }
]